pulsectl/__init__.py
pulsectl/_pulsectl.py
pulsectl/lookup.py
pulsectl/pulsectl.py
pulsectl/tests/__init__.py
pulsectl/tests/test_with_dummy_instance.py
pulsectl-24.11.0.dist-info/COPYING
pulsectl-24.11.0.dist-info/METADATA
pulsectl-24.11.0.dist-info/WHEEL
pulsectl-24.11.0.dist-info/top_level.txt
pulsectl-24.11.0.dist-info/RECORD
