Metadata-Version: 2.1
Name: pulsectl
Version: 24.11.0
Summary: Python high-level interface and ctypes-based bindings for PulseAudio (libpulse)
Home-page: http://github.com/mk-fg/python-pulse-control
Author: George Filipkin, Mike Kazantsev
Author-email: mk.fraggod@gmail.com
License: MIT
Keywords: pulseaudio,libpulse,pulse,pa,bindings,sound,audio,ctypes,control,mixer,volume,mute,source,sink
Classifier: Development Status :: 4 - Beta
Classifier: Intended Audience :: Developers
Classifier: License :: OSI Approved :: MIT License
Classifier: Operating System :: POSIX
Classifier: Operating System :: POSIX :: Linux
Classifier: Programming Language :: Python
Classifier: Programming Language :: Python :: 2
Classifier: Programming Language :: Python :: 3
Classifier: Topic :: Multimedia
Classifier: Topic :: Multimedia :: Sound/Audio
License-File: COPYING
